Metadata-Version: 2.1
Name: dataside
Version: 1.0.1
Summary: Lib dataside
Home-page: UNKNOWN
Author: dataside
Author-email: lucas.batista@dataside.com.br
License: MIT
Keywords: Lib dataside
Platform: UNKNOWN
Classifier: Development Status :: 5 - Production/Stable
Classifier: Intended Audience :: Education
Classifier: Operating System :: Microsoft :: Windows :: Windows 10
Classifier: Programming Language :: Python :: 3
